setup.cfg
setup.py
fv_email/__init__.py
fv_email.egg-info/PKG-INFO
fv_email.egg-info/SOURCES.txt
fv_email.egg-info/dependency_links.txt
fv_email.egg-info/not-zip-safe
fv_email.egg-info/requires.txt
fv_email.egg-info/top_level.txt